minisaml/__init__.py
minisaml/errors.py
minisaml/internal/__init__.py
minisaml/internal/constants.py
minisaml/internal/namespaces.py
minisaml/internal/saml.py
minisaml/internal/utils.py
minisaml/py.typed
minisaml/request.py
minisaml/response.py
minisaml-24.6.dist-info/LICENSE
minisaml-24.6.dist-info/METADATA
minisaml-24.6.dist-info/WHEEL
minisaml-24.6.dist-info/RECORD
