Metadata-Version: 2.1
Name: minisaml
Version: 24.6
Summary: Minimal SAML2 client
Home-page: https://github.com/HENNGE/minisaml
License: Apache-2.0
Author: Jonas Obrist
Author-email: jonas.obrist@hennge.com
Requires-Python: >=3.8,<4.0
Classifier: Development Status :: 5 - Production/Stable
Classifier: Intended Audience :: Developers
Classifier: License :: OSI Approved :: Apache Software License
Classifier: Programming Language :: Python :: 3
Classifier: Programming Language :: Python :: 3.8
Classifier: Programming Language :: Python :: 3.9
Classifier: Programming Language :: Python :: 3.10
Classifier: Programming Language :: Python :: 3.11
Classifier: Programming Language :: Python :: 3.12
Classifier: Programming Language :: Python :: 3 :: Only
Classifier: Typing :: Typed
Provides-Extra: docs
Requires-Dist: Sphinx (>=5,<6) ; extra == "docs"
Requires-Dist: furo (>=2022.6.21,<2023.0.0) ; extra == "docs"
Requires-Dist: lxml (>=5.0,<6.0)
Requires-Dist: minisignxml (>=24.6)
Requires-Dist: sphinxcontrib-mermaid (>=0.7.0,<0.8.0) ; extra == "docs"
Requires-Dist: yarl (>=1.4.2)
Project-URL: Documentation, https://minisaml.readthedocs.io
Project-URL: Repository, https://github.com/HENNGE/minisaml
